{
  "updated_at": "2026-05-27T15:04:04.234757",
  "total": 7,
  "hot_list": [
    {
      "title": "Startup Battlefield 200 申请今天截止：提名创始人或提交您的初创公司",
      "name": "Startup Battlefield 200 申请今天截止：提名创始人或提交您的初创公司",
      "title_zh": "Startup Battlefield 200 申请今天截止：提名创始人或提交您的初创公司",
      "url": "https://techcrunch.com/2026/05/27/startup-battlefield-200-applications-close-today-nominate-a-founder-or-submit-your-startup/",
      "type": "news",
      "source": "TechCrunch AI",
      "score": 15,
      "detail": "2026-05-27",
      "time": "2026-05-27",
      "description": "今天是申请或提名初创公司参加 Startup Battlefield 200 的最后一天。当时钟敲响晚上 11:59 时…",
      "subtitle": "今天是申请或提名初创公司参加 Startup Battlefield 200 的最后一天。当时钟敲响晚上 11:59 时…",
      "ai_summary": "今天是申请或提名初创公司参加 Startup Battlefield 200 的最后一天。当时钟敲响晚上 11:59 时…",
      "category": "资讯",
      "news_id": "2563f610a12c",
      "internal_url": "https://aihot.bt199.com/news/2563f610a12c/",
      "type_label": "📰 新闻"
    },
    {
      "title": "SOND 是 Bose 前睡眠主管创办的睡眠科技初创公司，以 700 万美元退出隐秘状态",
      "name": "SOND 是 Bose 前睡眠主管创办的睡眠科技初创公司，以 700 万美元退出隐秘状态",
      "title_zh": "SOND 是 Bose 前睡眠主管创办的睡眠科技初创公司，以 700 万美元退出隐秘状态",
      "url": "https://techcrunch.com/2026/05/27/sond-a-sleep-tech-startup-from-boses-former-head-of-sleep-exits-stealth-with-7m/",
      "type": "news",
      "source": "TechCrunch AI",
      "score": 15,
      "detail": "2026-05-27",
      "time": "2026-05-27",
      "description": "SOND 是一家由 Bose 前睡眠产品负责人领导的初创公司，凭借 700 万美元的资金开发其人工智能睡眠耳塞，脱颖而出…",
      "subtitle": "SOND 是一家由 Bose 前睡眠产品负责人领导的初创公司，凭借 700 万美元的资金开发其人工智能睡眠耳塞，脱颖而出…",
      "ai_summary": "SOND 是一家由 Bose 前睡眠产品负责人领导的初创公司，凭借 700 万美元的资金开发其人工智能睡眠耳塞，脱颖而出…",
      "category": "资讯",
      "news_id": "3f0ce030b5e2",
      "internal_url": "https://aihot.bt199.com/news/3f0ce030b5e2/",
      "type_label": "📰 新闻"
    },
    {
      "title": "Robinhood 将让你的人工智能代理交易股票并赚（或赔）很多钱",
      "name": "Robinhood 将让你的人工智能代理交易股票并赚（或赔）很多钱",
      "title_zh": "Robinhood 将让你的人工智能代理交易股票并赚（或赔）很多钱",
      "url": "https://www.theverge.com/ai-artificial-intelligence/938095/robinhood-ai-agent-stock-trading",
      "type": "news",
      "source": "The Verge AI",
      "score": 13,
      "detail": "2026-05-27",
      "time": "2026-05-27",
      "description": "Robinhood 正在向人工智能代理开放其交易平台。 Robinhood 在周三的一份声明中表示，交易者现在可以为人工…",
      "subtitle": "Robinhood 正在向人工智能代理开放其交易平台。 Robinhood 在周三的一份声明中表示，交易者现在可以为人工…",
      "ai_summary": "Robinhood 正在向人工智能代理开放其交易平台。 Robinhood 在周三的一份声明中表示，交易者现在可以为人工…",
      "category": "资讯",
      "news_id": "2422c4a58256",
      "internal_url": "https://aihot.bt199.com/news/2422c4a58256/",
      "type_label": "📰 新闻"
    },
    {
      "title": "这款智能喂鸟器捕捉到了我后院的更多戏剧",
      "name": "这款智能喂鸟器捕捉到了我后院的更多戏剧",
      "title_zh": "这款智能喂鸟器捕捉到了我后院的更多戏剧",
      "url": "https://www.theverge.com/tech/937628/coolfly-aura-smart-bird-feeder-review",
      "type": "news",
      "source": "The Verge AI",
      "score": 13,
      "detail": "2026-05-27",
      "time": "2026-05-27",
      "description": "自从搬到南卡罗来纳州的低地地区后，我就被无数与我们共享海岸的美丽鸟类所吸引——鱼鹰在通往我女儿学校的路旁高耸的巢穴中抚养…",
      "subtitle": "自从搬到南卡罗来纳州的低地地区后，我就被无数与我们共享海岸的美丽鸟类所吸引——鱼鹰在通往我女儿学校的路旁高耸的巢穴中抚养…",
      "ai_summary": "自从搬到南卡罗来纳州的低地地区后，我就被无数与我们共享海岸的美丽鸟类所吸引——鱼鹰在通往我女儿学校的路旁高耸的巢穴中抚养…",
      "category": "资讯",
      "news_id": "4faf7b5a927c",
      "internal_url": "https://aihot.bt199.com/news/4faf7b5a927c/",
      "type_label": "📰 新闻"
    },
    {
      "title": "重新思考代理人工智能时代的组织设计",
      "name": "重新思考代理人工智能时代的组织设计",
      "title_zh": "重新思考代理人工智能时代的组织设计",
      "url": "https://www.technologyreview.com/2026/05/26/1137584/rethinking-organizational-design-in-the-age-of-agentic-ai/",
      "type": "news",
      "source": "MIT Tech Review",
      "score": 13,
      "detail": "2026-05-26",
      "time": "2026-05-26",
      "description": "随着企业级人工智能代理的迅速普及，野心与执行力之间出现了脱节。 尽管 85% 的组织表示他们希望在未来三年内实现代理，但…",
      "subtitle": "随着企业级人工智能代理的迅速普及，野心与执行力之间出现了脱节。 尽管 85% 的组织表示他们希望在未来三年内实现代理，但…",
      "ai_summary": "随着企业级人工智能代理的迅速普及，野心与执行力之间出现了脱节。 尽管 85% 的组织表示他们希望在未来三年内实现代理，但…",
      "category": "资讯",
      "news_id": "b920d871e577",
      "internal_url": "https://aihot.bt199.com/news/b920d871e577/",
      "type_label": "📰 新闻"
    },
    {
      "title": "数以百万计的人工智能代理受到开源包中严重漏洞的威胁",
      "name": "数以百万计的人工智能代理受到开源包中严重漏洞的威胁",
      "title_zh": "数以百万计的人工智能代理受到开源包中严重漏洞的威胁",
      "url": "https://arstechnica.com/information-technology/2026/05/millions-of-ai-agents-imperiled-by-critical-vulnerability-in-open-source-package/",
      "type": "news",
      "source": "Ars Technica AI",
      "score": 11,
      "detail": "2026-05-26",
      "time": "2026-05-26",
      "description": "“BadHost”是在 Starlette 中发现的，该软件包每周下载量为 3.25 亿次",
      "subtitle": "“BadHost”是在 Starlette 中发现的，该软件包每周下载量为 3.25 亿次",
      "ai_summary": "“BadHost”是在 Starlette 中发现的，该软件包每周下载量为 3.25 亿次",
      "category": "资讯",
      "news_id": "336256f5c435",
      "internal_url": "https://aihot.bt199.com/news/336256f5c435/",
      "type_label": "📰 新闻"
    },
    {
      "title": "德克萨斯州 AG 起诉 Meta，指控 WhatsApp 不提供端到端加密",
      "name": "德克萨斯州 AG 起诉 Meta，指控 WhatsApp 不提供端到端加密",
      "title_zh": "德克萨斯州 AG 起诉 Meta，指控 WhatsApp 不提供端到端加密",
      "url": "https://arstechnica.com/security/2026/05/texas-ag-sues-meta-over-claims-that-whatsapp-doesnt-provide-end-to-end-encryption/",
      "type": "news",
      "source": "Ars Technica AI",
      "score": 6,
      "detail": "2026-05-22",
      "time": "2026-05-22",
      "description": "批评人士指出，美国参议院候选人提起的诉讼缺乏事实支持",
      "subtitle": "批评人士指出，美国参议院候选人提起的诉讼缺乏事实支持",
      "ai_summary": "批评人士指出，美国参议院候选人提起的诉讼缺乏事实支持",
      "category": "资讯",
      "news_id": "e24de95badde",
      "internal_url": "https://aihot.bt199.com/news/e24de95badde/",
      "type_label": "📰 新闻"
    }
  ],
  "top_20": [
    {
      "title": "Startup Battlefield 200 申请今天截止：提名创始人或提交您的初创公司",
      "name": "Startup Battlefield 200 申请今天截止：提名创始人或提交您的初创公司",
      "title_zh": "Startup Battlefield 200 申请今天截止：提名创始人或提交您的初创公司",
      "url": "https://techcrunch.com/2026/05/27/startup-battlefield-200-applications-close-today-nominate-a-founder-or-submit-your-startup/",
      "type": "news",
      "source": "TechCrunch AI",
      "score": 15,
      "detail": "2026-05-27",
      "time": "2026-05-27",
      "description": "今天是申请或提名初创公司参加 Startup Battlefield 200 的最后一天。当时钟敲响晚上 11:59 时…",
      "subtitle": "今天是申请或提名初创公司参加 Startup Battlefield 200 的最后一天。当时钟敲响晚上 11:59 时…",
      "ai_summary": "今天是申请或提名初创公司参加 Startup Battlefield 200 的最后一天。当时钟敲响晚上 11:59 时…",
      "category": "资讯",
      "news_id": "2563f610a12c",
      "internal_url": "https://aihot.bt199.com/news/2563f610a12c/",
      "type_label": "📰 新闻"
    },
    {
      "title": "SOND 是 Bose 前睡眠主管创办的睡眠科技初创公司，以 700 万美元退出隐秘状态",
      "name": "SOND 是 Bose 前睡眠主管创办的睡眠科技初创公司，以 700 万美元退出隐秘状态",
      "title_zh": "SOND 是 Bose 前睡眠主管创办的睡眠科技初创公司，以 700 万美元退出隐秘状态",
      "url": "https://techcrunch.com/2026/05/27/sond-a-sleep-tech-startup-from-boses-former-head-of-sleep-exits-stealth-with-7m/",
      "type": "news",
      "source": "TechCrunch AI",
      "score": 15,
      "detail": "2026-05-27",
      "time": "2026-05-27",
      "description": "SOND 是一家由 Bose 前睡眠产品负责人领导的初创公司，凭借 700 万美元的资金开发其人工智能睡眠耳塞，脱颖而出…",
      "subtitle": "SOND 是一家由 Bose 前睡眠产品负责人领导的初创公司，凭借 700 万美元的资金开发其人工智能睡眠耳塞，脱颖而出…",
      "ai_summary": "SOND 是一家由 Bose 前睡眠产品负责人领导的初创公司，凭借 700 万美元的资金开发其人工智能睡眠耳塞，脱颖而出…",
      "category": "资讯",
      "news_id": "3f0ce030b5e2",
      "internal_url": "https://aihot.bt199.com/news/3f0ce030b5e2/",
      "type_label": "📰 新闻"
    },
    {
      "title": "Robinhood 将让你的人工智能代理交易股票并赚（或赔）很多钱",
      "name": "Robinhood 将让你的人工智能代理交易股票并赚（或赔）很多钱",
      "title_zh": "Robinhood 将让你的人工智能代理交易股票并赚（或赔）很多钱",
      "url": "https://www.theverge.com/ai-artificial-intelligence/938095/robinhood-ai-agent-stock-trading",
      "type": "news",
      "source": "The Verge AI",
      "score": 13,
      "detail": "2026-05-27",
      "time": "2026-05-27",
      "description": "Robinhood 正在向人工智能代理开放其交易平台。 Robinhood 在周三的一份声明中表示，交易者现在可以为人工…",
      "subtitle": "Robinhood 正在向人工智能代理开放其交易平台。 Robinhood 在周三的一份声明中表示，交易者现在可以为人工…",
      "ai_summary": "Robinhood 正在向人工智能代理开放其交易平台。 Robinhood 在周三的一份声明中表示，交易者现在可以为人工…",
      "category": "资讯",
      "news_id": "2422c4a58256",
      "internal_url": "https://aihot.bt199.com/news/2422c4a58256/",
      "type_label": "📰 新闻"
    },
    {
      "title": "这款智能喂鸟器捕捉到了我后院的更多戏剧",
      "name": "这款智能喂鸟器捕捉到了我后院的更多戏剧",
      "title_zh": "这款智能喂鸟器捕捉到了我后院的更多戏剧",
      "url": "https://www.theverge.com/tech/937628/coolfly-aura-smart-bird-feeder-review",
      "type": "news",
      "source": "The Verge AI",
      "score": 13,
      "detail": "2026-05-27",
      "time": "2026-05-27",
      "description": "自从搬到南卡罗来纳州的低地地区后，我就被无数与我们共享海岸的美丽鸟类所吸引——鱼鹰在通往我女儿学校的路旁高耸的巢穴中抚养…",
      "subtitle": "自从搬到南卡罗来纳州的低地地区后，我就被无数与我们共享海岸的美丽鸟类所吸引——鱼鹰在通往我女儿学校的路旁高耸的巢穴中抚养…",
      "ai_summary": "自从搬到南卡罗来纳州的低地地区后，我就被无数与我们共享海岸的美丽鸟类所吸引——鱼鹰在通往我女儿学校的路旁高耸的巢穴中抚养…",
      "category": "资讯",
      "news_id": "4faf7b5a927c",
      "internal_url": "https://aihot.bt199.com/news/4faf7b5a927c/",
      "type_label": "📰 新闻"
    },
    {
      "title": "重新思考代理人工智能时代的组织设计",
      "name": "重新思考代理人工智能时代的组织设计",
      "title_zh": "重新思考代理人工智能时代的组织设计",
      "url": "https://www.technologyreview.com/2026/05/26/1137584/rethinking-organizational-design-in-the-age-of-agentic-ai/",
      "type": "news",
      "source": "MIT Tech Review",
      "score": 13,
      "detail": "2026-05-26",
      "time": "2026-05-26",
      "description": "随着企业级人工智能代理的迅速普及，野心与执行力之间出现了脱节。 尽管 85% 的组织表示他们希望在未来三年内实现代理，但…",
      "subtitle": "随着企业级人工智能代理的迅速普及，野心与执行力之间出现了脱节。 尽管 85% 的组织表示他们希望在未来三年内实现代理，但…",
      "ai_summary": "随着企业级人工智能代理的迅速普及，野心与执行力之间出现了脱节。 尽管 85% 的组织表示他们希望在未来三年内实现代理，但…",
      "category": "资讯",
      "news_id": "b920d871e577",
      "internal_url": "https://aihot.bt199.com/news/b920d871e577/",
      "type_label": "📰 新闻"
    },
    {
      "title": "数以百万计的人工智能代理受到开源包中严重漏洞的威胁",
      "name": "数以百万计的人工智能代理受到开源包中严重漏洞的威胁",
      "title_zh": "数以百万计的人工智能代理受到开源包中严重漏洞的威胁",
      "url": "https://arstechnica.com/information-technology/2026/05/millions-of-ai-agents-imperiled-by-critical-vulnerability-in-open-source-package/",
      "type": "news",
      "source": "Ars Technica AI",
      "score": 11,
      "detail": "2026-05-26",
      "time": "2026-05-26",
      "description": "“BadHost”是在 Starlette 中发现的，该软件包每周下载量为 3.25 亿次",
      "subtitle": "“BadHost”是在 Starlette 中发现的，该软件包每周下载量为 3.25 亿次",
      "ai_summary": "“BadHost”是在 Starlette 中发现的，该软件包每周下载量为 3.25 亿次",
      "category": "资讯",
      "news_id": "336256f5c435",
      "internal_url": "https://aihot.bt199.com/news/336256f5c435/",
      "type_label": "📰 新闻"
    },
    {
      "title": "德克萨斯州 AG 起诉 Meta，指控 WhatsApp 不提供端到端加密",
      "name": "德克萨斯州 AG 起诉 Meta，指控 WhatsApp 不提供端到端加密",
      "title_zh": "德克萨斯州 AG 起诉 Meta，指控 WhatsApp 不提供端到端加密",
      "url": "https://arstechnica.com/security/2026/05/texas-ag-sues-meta-over-claims-that-whatsapp-doesnt-provide-end-to-end-encryption/",
      "type": "news",
      "source": "Ars Technica AI",
      "score": 6,
      "detail": "2026-05-22",
      "time": "2026-05-22",
      "description": "批评人士指出，美国参议院候选人提起的诉讼缺乏事实支持",
      "subtitle": "批评人士指出，美国参议院候选人提起的诉讼缺乏事实支持",
      "ai_summary": "批评人士指出，美国参议院候选人提起的诉讼缺乏事实支持",
      "category": "资讯",
      "news_id": "e24de95badde",
      "internal_url": "https://aihot.bt199.com/news/e24de95badde/",
      "type_label": "📰 新闻"
    }
  ],
  "type_stats": {
    "tool": 0,
    "project": 0,
    "news": 7,
    "model": 0
  },
  "items": [
    {
      "title": "Startup Battlefield 200 申请今天截止：提名创始人或提交您的初创公司",
      "name": "Startup Battlefield 200 申请今天截止：提名创始人或提交您的初创公司",
      "title_zh": "Startup Battlefield 200 申请今天截止：提名创始人或提交您的初创公司",
      "url": "https://techcrunch.com/2026/05/27/startup-battlefield-200-applications-close-today-nominate-a-founder-or-submit-your-startup/",
      "type": "news",
      "source": "TechCrunch AI",
      "score": 15,
      "detail": "2026-05-27",
      "time": "2026-05-27",
      "description": "今天是申请或提名初创公司参加 Startup Battlefield 200 的最后一天。当时钟敲响晚上 11:59 时…",
      "subtitle": "今天是申请或提名初创公司参加 Startup Battlefield 200 的最后一天。当时钟敲响晚上 11:59 时…",
      "ai_summary": "今天是申请或提名初创公司参加 Startup Battlefield 200 的最后一天。当时钟敲响晚上 11:59 时…",
      "category": "资讯",
      "news_id": "2563f610a12c",
      "internal_url": "https://aihot.bt199.com/news/2563f610a12c/",
      "type_label": "📰 新闻"
    },
    {
      "title": "SOND 是 Bose 前睡眠主管创办的睡眠科技初创公司，以 700 万美元退出隐秘状态",
      "name": "SOND 是 Bose 前睡眠主管创办的睡眠科技初创公司，以 700 万美元退出隐秘状态",
      "title_zh": "SOND 是 Bose 前睡眠主管创办的睡眠科技初创公司，以 700 万美元退出隐秘状态",
      "url": "https://techcrunch.com/2026/05/27/sond-a-sleep-tech-startup-from-boses-former-head-of-sleep-exits-stealth-with-7m/",
      "type": "news",
      "source": "TechCrunch AI",
      "score": 15,
      "detail": "2026-05-27",
      "time": "2026-05-27",
      "description": "SOND 是一家由 Bose 前睡眠产品负责人领导的初创公司，凭借 700 万美元的资金开发其人工智能睡眠耳塞，脱颖而出…",
      "subtitle": "SOND 是一家由 Bose 前睡眠产品负责人领导的初创公司，凭借 700 万美元的资金开发其人工智能睡眠耳塞，脱颖而出…",
      "ai_summary": "SOND 是一家由 Bose 前睡眠产品负责人领导的初创公司，凭借 700 万美元的资金开发其人工智能睡眠耳塞，脱颖而出…",
      "category": "资讯",
      "news_id": "3f0ce030b5e2",
      "internal_url": "https://aihot.bt199.com/news/3f0ce030b5e2/",
      "type_label": "📰 新闻"
    },
    {
      "title": "Robinhood 将让你的人工智能代理交易股票并赚（或赔）很多钱",
      "name": "Robinhood 将让你的人工智能代理交易股票并赚（或赔）很多钱",
      "title_zh": "Robinhood 将让你的人工智能代理交易股票并赚（或赔）很多钱",
      "url": "https://www.theverge.com/ai-artificial-intelligence/938095/robinhood-ai-agent-stock-trading",
      "type": "news",
      "source": "The Verge AI",
      "score": 13,
      "detail": "2026-05-27",
      "time": "2026-05-27",
      "description": "Robinhood 正在向人工智能代理开放其交易平台。 Robinhood 在周三的一份声明中表示，交易者现在可以为人工…",
      "subtitle": "Robinhood 正在向人工智能代理开放其交易平台。 Robinhood 在周三的一份声明中表示，交易者现在可以为人工…",
      "ai_summary": "Robinhood 正在向人工智能代理开放其交易平台。 Robinhood 在周三的一份声明中表示，交易者现在可以为人工…",
      "category": "资讯",
      "news_id": "2422c4a58256",
      "internal_url": "https://aihot.bt199.com/news/2422c4a58256/",
      "type_label": "📰 新闻"
    },
    {
      "title": "这款智能喂鸟器捕捉到了我后院的更多戏剧",
      "name": "这款智能喂鸟器捕捉到了我后院的更多戏剧",
      "title_zh": "这款智能喂鸟器捕捉到了我后院的更多戏剧",
      "url": "https://www.theverge.com/tech/937628/coolfly-aura-smart-bird-feeder-review",
      "type": "news",
      "source": "The Verge AI",
      "score": 13,
      "detail": "2026-05-27",
      "time": "2026-05-27",
      "description": "自从搬到南卡罗来纳州的低地地区后，我就被无数与我们共享海岸的美丽鸟类所吸引——鱼鹰在通往我女儿学校的路旁高耸的巢穴中抚养…",
      "subtitle": "自从搬到南卡罗来纳州的低地地区后，我就被无数与我们共享海岸的美丽鸟类所吸引——鱼鹰在通往我女儿学校的路旁高耸的巢穴中抚养…",
      "ai_summary": "自从搬到南卡罗来纳州的低地地区后，我就被无数与我们共享海岸的美丽鸟类所吸引——鱼鹰在通往我女儿学校的路旁高耸的巢穴中抚养…",
      "category": "资讯",
      "news_id": "4faf7b5a927c",
      "internal_url": "https://aihot.bt199.com/news/4faf7b5a927c/",
      "type_label": "📰 新闻"
    },
    {
      "title": "重新思考代理人工智能时代的组织设计",
      "name": "重新思考代理人工智能时代的组织设计",
      "title_zh": "重新思考代理人工智能时代的组织设计",
      "url": "https://www.technologyreview.com/2026/05/26/1137584/rethinking-organizational-design-in-the-age-of-agentic-ai/",
      "type": "news",
      "source": "MIT Tech Review",
      "score": 13,
      "detail": "2026-05-26",
      "time": "2026-05-26",
      "description": "随着企业级人工智能代理的迅速普及，野心与执行力之间出现了脱节。 尽管 85% 的组织表示他们希望在未来三年内实现代理，但…",
      "subtitle": "随着企业级人工智能代理的迅速普及，野心与执行力之间出现了脱节。 尽管 85% 的组织表示他们希望在未来三年内实现代理，但…",
      "ai_summary": "随着企业级人工智能代理的迅速普及，野心与执行力之间出现了脱节。 尽管 85% 的组织表示他们希望在未来三年内实现代理，但…",
      "category": "资讯",
      "news_id": "b920d871e577",
      "internal_url": "https://aihot.bt199.com/news/b920d871e577/",
      "type_label": "📰 新闻"
    },
    {
      "title": "数以百万计的人工智能代理受到开源包中严重漏洞的威胁",
      "name": "数以百万计的人工智能代理受到开源包中严重漏洞的威胁",
      "title_zh": "数以百万计的人工智能代理受到开源包中严重漏洞的威胁",
      "url": "https://arstechnica.com/information-technology/2026/05/millions-of-ai-agents-imperiled-by-critical-vulnerability-in-open-source-package/",
      "type": "news",
      "source": "Ars Technica AI",
      "score": 11,
      "detail": "2026-05-26",
      "time": "2026-05-26",
      "description": "“BadHost”是在 Starlette 中发现的，该软件包每周下载量为 3.25 亿次",
      "subtitle": "“BadHost”是在 Starlette 中发现的，该软件包每周下载量为 3.25 亿次",
      "ai_summary": "“BadHost”是在 Starlette 中发现的，该软件包每周下载量为 3.25 亿次",
      "category": "资讯",
      "news_id": "336256f5c435",
      "internal_url": "https://aihot.bt199.com/news/336256f5c435/",
      "type_label": "📰 新闻"
    },
    {
      "title": "德克萨斯州 AG 起诉 Meta，指控 WhatsApp 不提供端到端加密",
      "name": "德克萨斯州 AG 起诉 Meta，指控 WhatsApp 不提供端到端加密",
      "title_zh": "德克萨斯州 AG 起诉 Meta，指控 WhatsApp 不提供端到端加密",
      "url": "https://arstechnica.com/security/2026/05/texas-ag-sues-meta-over-claims-that-whatsapp-doesnt-provide-end-to-end-encryption/",
      "type": "news",
      "source": "Ars Technica AI",
      "score": 6,
      "detail": "2026-05-22",
      "time": "2026-05-22",
      "description": "批评人士指出，美国参议院候选人提起的诉讼缺乏事实支持",
      "subtitle": "批评人士指出，美国参议院候选人提起的诉讼缺乏事实支持",
      "ai_summary": "批评人士指出，美国参议院候选人提起的诉讼缺乏事实支持",
      "category": "资讯",
      "news_id": "e24de95badde",
      "internal_url": "https://aihot.bt199.com/news/e24de95badde/",
      "type_label": "📰 新闻"
    }
  ]
}
